{
"meta":{"test_sets":[],"test_metrics":[],"learn_metrics":[{"best_value":"Min","name":"Logloss"}],"launch_mode":"Train","parameters":"","iteration_count":100,"learn_sets":["learn"],"name":"experiment"},
"iterations":[
{"learn":[0.6677025951],"iteration":0,"passed_time":0.06136289658,"remaining_time":6.074926761},
{"learn":[0.6395482101],"iteration":1,"passed_time":0.06728742768,"remaining_time":3.297083956},
{"learn":[0.6165335545],"iteration":2,"passed_time":0.07543992382,"remaining_time":2.439224203},
{"learn":[0.6030354703],"iteration":3,"passed_time":0.08181688987,"remaining_time":1.963605357},
{"learn":[0.5883073782],"iteration":4,"passed_time":0.08945269846,"remaining_time":1.699601271},
{"learn":[0.5682312864],"iteration":5,"passed_time":0.09836030845,"remaining_time":1.540978166},
{"learn":[0.5546629268],"iteration":6,"passed_time":0.1057425651,"remaining_time":1.404865508},
{"learn":[0.5433390697],"iteration":7,"passed_time":0.1136971783,"remaining_time":1.30751755},
{"learn":[0.5290191402],"iteration":8,"passed_time":0.1225032008,"remaining_time":1.238643475},
{"learn":[0.520788909],"iteration":9,"passed_time":0.1392221265,"remaining_time":1.252999139},
{"learn":[0.5107293938],"iteration":10,"passed_time":0.1482390742,"remaining_time":1.199388873},
{"learn":[0.5001735343],"iteration":11,"passed_time":0.155770712,"remaining_time":1.142318554},
{"learn":[0.4922317361],"iteration":12,"passed_time":0.1630197966,"remaining_time":1.090978639},
{"learn":[0.4821265922],"iteration":13,"passed_time":0.1699733693,"remaining_time":1.044122126},
{"learn":[0.4734449562],"iteration":14,"passed_time":0.177026696,"remaining_time":1.003151277},
{"learn":[0.4658176669],"iteration":15,"passed_time":0.1838858899,"remaining_time":0.9654009218},
{"learn":[0.4611823985],"iteration":16,"passed_time":0.1914727798,"remaining_time":0.9348376897},
{"learn":[0.4567145234],"iteration":17,"passed_time":0.1982058436,"remaining_time":0.9029377319},
{"learn":[0.4508344313],"iteration":18,"passed_time":0.2047597335,"remaining_time":0.8729230742},
{"learn":[0.444184969],"iteration":19,"passed_time":0.21151959,"remaining_time":0.8460783599},
{"learn":[0.4395924874],"iteration":20,"passed_time":0.2183116561,"remaining_time":0.8212676588},
{"learn":[0.4349895669],"iteration":21,"passed_time":0.2311086317,"remaining_time":0.8193851486},
{"learn":[0.4321672835],"iteration":22,"passed_time":0.2422084552,"remaining_time":0.8108717849},
{"learn":[0.4280429313],"iteration":23,"passed_time":0.2508418875,"remaining_time":0.7943326437},
{"learn":[0.4253363812],"iteration":24,"passed_time":0.2591264306,"remaining_time":0.7773792919},
{"learn":[0.421542679],"iteration":25,"passed_time":0.2668549096,"remaining_time":0.7595101274},
{"learn":[0.4176252247],"iteration":26,"passed_time":0.2750134894,"remaining_time":0.7435549897},
{"learn":[0.4144067094],"iteration":27,"passed_time":0.2839741848,"remaining_time":0.7302193324},
{"learn":[0.4115087093],"iteration":28,"passed_time":0.2931194711,"remaining_time":0.7176373258},
{"learn":[0.4093181549],"iteration":29,"passed_time":0.301744778,"remaining_time":0.7040711487},
{"learn":[0.4058492925],"iteration":30,"passed_time":0.3099079829,"remaining_time":0.6897951878},
{"learn":[0.4037741108],"iteration":31,"passed_time":0.3203514883,"remaining_time":0.6807469126},
{"learn":[0.4002858733],"iteration":32,"passed_time":0.3325368141,"remaining_time":0.6751505013},
{"learn":[0.3983971508],"iteration":33,"passed_time":0.355308401,"remaining_time":0.6897163079},
{"learn":[0.396596304],"iteration":34,"passed_time":0.3704771807,"remaining_time":0.6880290499},
{"learn":[0.3944686059],"iteration":35,"passed_time":0.3837825101,"remaining_time":0.682280018},
{"learn":[0.3919758566],"iteration":36,"passed_time":0.3943779383,"remaining_time":0.6715083815},
{"learn":[0.3880480933],"iteration":37,"passed_time":0.4012467576,"remaining_time":0.6546657624},
{"learn":[0.385505386],"iteration":38,"passed_time":0.4072586672,"remaining_time":0.6369943257},
{"learn":[0.3817721108],"iteration":39,"passed_time":0.4148535158,"remaining_time":0.6222802737},
{"learn":[0.3798168609],"iteration":40,"passed_time":0.4220416397,"remaining_time":0.6073282132},
{"learn":[0.3780594676],"iteration":41,"passed_time":0.4299568345,"remaining_time":0.5937499144},
{"learn":[0.3760153038],"iteration":42,"passed_time":0.4372248783,"remaining_time":0.5795771642},
{"learn":[0.3742461027],"iteration":43,"passed_time":0.4439471083,"remaining_time":0.5650235923},
{"learn":[0.3720302344],"iteration":44,"passed_time":0.4519283475,"remaining_time":0.5523568692},
{"learn":[0.3700156288],"iteration":45,"passed_time":0.4602844352,"remaining_time":0.5403339022},
{"learn":[0.3674981091],"iteration":46,"passed_time":0.4675051437,"remaining_time":0.5271866514},
{"learn":[0.3655507028],"iteration":47,"passed_time":0.4739608629,"remaining_time":0.5134576015},
{"learn":[0.3635262337],"iteration":48,"passed_time":0.4804560421,"remaining_time":0.5000664928},
{"learn":[0.3617830827],"iteration":49,"passed_time":0.4883759038,"remaining_time":0.4883759038},
{"learn":[0.3599942371],"iteration":50,"passed_time":0.4950555488,"remaining_time":0.4756416057},
{"learn":[0.3589474481],"iteration":51,"passed_time":0.5022755489,"remaining_time":0.4636389682},
{"learn":[0.3570680159],"iteration":52,"passed_time":0.5092062456,"remaining_time":0.4515602556},
{"learn":[0.3538619616],"iteration":53,"passed_time":0.5164489967,"remaining_time":0.4399380342},
{"learn":[0.352153615],"iteration":54,"passed_time":0.5253951916,"remaining_time":0.4298687931},
{"learn":[0.350212791],"iteration":55,"passed_time":0.5336211907,"remaining_time":0.4192737927},
{"learn":[0.3486327157],"iteration":56,"passed_time":0.5413606285,"remaining_time":0.4083948601},
{"learn":[0.3471392169],"iteration":57,"passed_time":0.5489901451,"remaining_time":0.3975445879},
{"learn":[0.3455782433],"iteration":58,"passed_time":0.556880839,"remaining_time":0.3869849898},
{"learn":[0.342185589],"iteration":59,"passed_time":0.5634092279,"remaining_time":0.3756061519},
{"learn":[0.3402940204],"iteration":60,"passed_time":0.5705921432,"remaining_time":0.3648048128},
{"learn":[0.3390255616],"iteration":61,"passed_time":0.5784394186,"remaining_time":0.3545273856},
{"learn":[0.3375118931],"iteration":62,"passed_time":0.5887868368,"remaining_time":0.3457954438},
{"learn":[0.3353882893],"iteration":63,"passed_time":0.5975373988,"remaining_time":0.3361147868},
{"learn":[0.3337480049],"iteration":64,"passed_time":0.6069666965,"remaining_time":0.3268282212},
{"learn":[0.3319195818],"iteration":65,"passed_time":0.6147426774,"remaining_time":0.3166856217},
{"learn":[0.3301306695],"iteration":66,"passed_time":0.6236127026,"remaining_time":0.3071525252},
{"learn":[0.3286901463],"iteration":67,"passed_time":0.6319022459,"remaining_time":0.2973657628},
{"learn":[0.3272909162],"iteration":68,"passed_time":0.6408636081,"remaining_time":0.2879242297},
{"learn":[0.3259298234],"iteration":69,"passed_time":0.6485172507,"remaining_time":0.2779359646},
{"learn":[0.3244099742],"iteration":70,"passed_time":0.6568349202,"remaining_time":0.2682846857},
{"learn":[0.3232531319],"iteration":71,"passed_time":0.664491063,"remaining_time":0.2584131912},
{"learn":[0.3214159802],"iteration":72,"passed_time":0.6729539467,"remaining_time":0.2489007748},
{"learn":[0.3201242135],"iteration":73,"passed_time":0.6814973336,"remaining_time":0.2394450091},
{"learn":[0.3188716567],"iteration":74,"passed_time":0.6905989514,"remaining_time":0.2301996505},
{"learn":[0.3176374239],"iteration":75,"passed_time":0.6993875983,"remaining_time":0.2208592416},
{"learn":[0.316741228],"iteration":76,"passed_time":0.7068655255,"remaining_time":0.2111416505},
{"learn":[0.3151488027],"iteration":77,"passed_time":0.7146792996,"remaining_time":0.2015762127},
{"learn":[0.314125769],"iteration":78,"passed_time":0.7227059157,"remaining_time":0.1921116991},
{"learn":[0.3124426459],"iteration":79,"passed_time":0.730757491,"remaining_time":0.1826893728},
{"learn":[0.3107072921],"iteration":80,"passed_time":0.7390172832,"remaining_time":0.1733497331},
{"learn":[0.3092195524],"iteration":81,"passed_time":0.7469446869,"remaining_time":0.1639634679},
{"learn":[0.307614898],"iteration":82,"passed_time":0.7562480629,"remaining_time":0.1548941816},
{"learn":[0.3059487437],"iteration":83,"passed_time":0.7639145811,"remaining_time":0.1455075392},
{"learn":[0.3045685283],"iteration":84,"passed_time":0.7721012869,"remaining_time":0.1362531683},
{"learn":[0.3029399095],"iteration":85,"passed_time":0.7803344113,"remaining_time":0.1270311832},
{"learn":[0.3013204772],"iteration":86,"passed_time":0.7907900422,"remaining_time":0.1181640293},
{"learn":[0.2999806054],"iteration":87,"passed_time":0.8001837552,"remaining_time":0.1091159666},
{"learn":[0.2986459806],"iteration":88,"passed_time":0.8075785123,"remaining_time":0.09981307456},
{"learn":[0.2970404422],"iteration":89,"passed_time":0.8151653606,"remaining_time":0.09057392896},
{"learn":[0.2960141767],"iteration":90,"passed_time":0.8235076978,"remaining_time":0.08144581626},
{"learn":[0.2949628448],"iteration":91,"passed_time":0.8322082994,"remaining_time":0.07236593908},
{"learn":[0.2934016293],"iteration":92,"passed_time":0.8397965644,"remaining_time":0.06321049409},
{"learn":[0.2924597035],"iteration":93,"passed_time":0.8475900877,"remaining_time":0.05410149496},
{"learn":[0.290706973],"iteration":94,"passed_time":0.8550333885,"remaining_time":0.04500175729},
{"learn":[0.2891119732],"iteration":95,"passed_time":0.8633500163,"remaining_time":0.03597291735},
{"learn":[0.2875401107],"iteration":96,"passed_time":0.8706327273,"remaining_time":0.02692678538},
{"learn":[0.2862323858],"iteration":97,"passed_time":0.8781619482,"remaining_time":0.01792167241},
{"learn":[0.2846427581],"iteration":98,"passed_time":0.8865507873,"remaining_time":0.008955058457},
{"learn":[0.2836686253],"iteration":99,"passed_time":0.8949923367,"remaining_time":0}
]}